src/pc.v
module pc(
    input clk,
    input reset,
    input  [31:0] pc_next,
  output reg [31:0] pc
);

always @(posedge clk) begin
    if (reset)
      pc <= 32'b0;
    else
      pc <= pc_next;
  end

  endmodule

tb/tb_pc.v
module tb_pc;
reg clk;
reg reset;
reg  [31:0] pc_next;
  wire [31:0] pc;

pc uut(.clk(clk), .reset(reset), .pc_next(pc_next), .pc(pc));


 initial clk =0;
  always #5 clk = ~clk;

initial begin
    $dumpfile("tb/tb_pc.vcd");
    $dumpvars(0, tb_pc);

//Test reset
reset =1; pc_next= 32'd0; #10;
$display("After reset: pc = %0d (expect 0)", pc);

//release reset, increment by 4
 reset = 0; pc_next = pc + 4; #10;
    $display("After cycle 1: pc = %0d (expect 4)", pc);

    pc_next = pc + 4; #10;
    $display("After cycle 2: pc = %0d (expect 8)", pc);

    pc_next = pc + 4; #10;
    $display("After cycle 3: pc = %0d (expect 12)", pc);

    $finish;
  end

endmodule

tb/tb_pc.vcd
$date
	Thu Jun 25 15:56:56 2026
$end
$version
	Icarus Verilog
$end
$timescale
	1s
$end
$scope module tb_pc $end
$var wire 32 ! pc [31:0] $end
$var reg 1 " clk $end
$var reg 32 # pc_next [31:0] $end
$var reg 1 $ reset $end
$scope module uut $end
$var wire 1 " clk $end
$var wire 32 % pc_next [31:0] $end
$var wire 1 $ reset $end
$var reg 32 & pc [31:0] $end
$upscope $end
$upscope $end
$enddefinitions $end
$comment Show the parameter values. $end
$dumpall
$end
#0
$dumpvars
bx &
b0 %
1$
b0 #
0"
bx !
$end
#5
b0 !
b0 &
1"
#10
0"
b100 #
b100 %
0$
#15
b100 !
b100 &
1"
#20
0"
b1000 #
b1000 %
#25
b1000 !
b1000 &
1"
#30
0"
b1100 #
b1100 %
#35
b1100 !
b1100 &
1"
